helptasker_common/__init__.py
helptasker_common/context.py
helptasker_common/handlers/__init__.py
helptasker_common/handlers/healthcheck.py
helptasker_common/http_base_client.py
helptasker_common/instrumentation.py
helptasker_common/logger.py
helptasker_common/middlewares.py
helptasker_common/py.typed
helptasker_common/settings.py
helptasker_common/trace.py
helptasker_common-0.2.1.dist-info/LICENSE
helptasker_common-0.2.1.dist-info/METADATA
helptasker_common-0.2.1.dist-info/WHEEL
helptasker_common-0.2.1.dist-info/RECORD
